README.md
setup.py
meduse/__init__.py
meduse/__main__.py
meduse/bsfilters.py
meduse_CERTIC.egg-info/PKG-INFO
meduse_CERTIC.egg-info/SOURCES.txt
meduse_CERTIC.egg-info/dependency_links.txt
meduse_CERTIC.egg-info/entry_points.txt
meduse_CERTIC.egg-info/requires.txt
meduse_CERTIC.egg-info/top_level.txt