Metadata-Version: 2.1
Name: meduse-CERTIC
Version: 0.0.5
Summary: Outil en ligne de commande destiné à réaliser des copies statiques des projets du Pôle Document Numérique.
Home-page: https://git.unicaen.fr/pdn-certic/advStatificator
Author: Mickaël Desfrênes
Author-email: mickael.desfrenes@unicaen.fr
Classifier: Programming Language :: Python :: 3
Classifier: License :: OSI Approved :: MIT License
Classifier: Operating System :: OS Independent
Requires-Python: >=3.6
